{
    "1": {
        "notification_id": "1",
        "recipient_user_id": "265",
        "event_type": "permission_granted",
        "message": "Alert 1 for user.",
        "related_entity_type": "pages",
        "related_entity_id": null,
        "sender_user_id": "210",
        "channel": "system",
        "delivery_status": "pending",
        "created_at": "2023-10-28T11:29:30",
        "sent_at": null,
        "read_at": null,
        "metadata": "{\"is_priority\": \"true\"}"
    },
    "2": {
        "notification_id": "2",
        "recipient_user_id": "80",
        "event_type": "new_mention",
        "message": "Alert 2 for user.",
        "related_entity_type": "spaces",
        "related_entity_id": null,
        "sender_user_id": "227",
        "channel": "email",
        "delivery_status": "read",
        "created_at": "2023-10-28T21:02:29",
        "sent_at": "2023-11-02T13:22:30",
        "read_at": "2023-11-08T15:54:07",
        "metadata": "{\"is_priority\": \"true\"}"
    },
    "3": {
        "notification_id": "3",
        "recipient_user_id": "187",
        "event_type": "page_updated",
        "message": "Alert 3 for user.",
        "related_entity_type": "spaces",
        "related_entity_id": null,
        "sender_user_id": "236",
        "channel": "system",
        "delivery_status": "sent",
        "created_at": "2023-10-29T17:56:20",
        "sent_at": "2023-11-04T11:55:42",
        "read_at": null,
        "metadata": "{\"is_priority\": \"false\"}"
    },
    "4": {
        "notification_id": "4",
        "recipient_user_id": "163",
        "event_type": "new_mention",
        "message": "Alert 4 for user.",
        "related_entity_type": "spaces",
        "related_entity_id": null,
        "sender_user_id": "138",
        "channel": "system",
        "delivery_status": "read",
        "created_at": "2023-10-30T18:20:06",
        "sent_at": "2023-11-04T10:31:51",
        "read_at": "2023-11-11T00:42:39",
        "metadata": "{\"is_priority\": \"false\"}"
    },
    "5": {
        "notification_id": "5",
        "recipient_user_id": "281",
        "event_type": "permission_granted",
        "message": "Alert 5 for user.",
        "related_entity_type": "pages",
        "related_entity_id": null,
        "sender_user_id": "271",
        "channel": "email",
        "delivery_status": "sent",
        "created_at": "2023-10-28T10:28:07",
        "sent_at": "2023-11-04T07:40:02",
        "read_at": null,
        "metadata": "{\"is_priority\": \"false\"}"
    },
    "6": {
        "notification_id": "6",
        "recipient_user_id": "163",
        "event_type": "page_updated",
        "message": "Alert 6 for user.",
        "related_entity_type": "users",
        "related_entity_id": null,
        "sender_user_id": "260",
        "channel": "email",
        "delivery_status": "failed",
        "created_at": "2023-11-02T17:45:38",
        "sent_at": "2023-11-04T02:14:04",
        "read_at": null,
        "metadata": "{\"is_priority\": \"true\"}"
    },
    "7": {
        "notification_id": "7",
        "recipient_user_id": "268",
        "event_type": "page_updated",
        "message": "Alert 7 for user.",
        "related_entity_type": "spaces",
        "related_entity_id": null,
        "sender_user_id": "69",
        "channel": "system",
        "delivery_status": "failed",
        "created_at": "2023-10-30T20:40:24",
        "sent_at": "2023-11-08T14:36:12",
        "read_at": null,
        "metadata": "{\"is_priority\": \"true\"}"
    },
    "8": {
        "notification_id": "8",
        "recipient_user_id": "88",
        "event_type": "permission_granted",
        "message": "Alert 8 for user.",
        "related_entity_type": "users",
        "related_entity_id": null,
        "sender_user_id": "147",
        "channel": "system",
        "delivery_status": "failed",
        "created_at": "2023-11-03T14:16:07",
        "sent_at": "2023-11-06T03:41:14",
        "read_at": null,
        "metadata": "{\"is_priority\": \"false\"}"
    },
    "9": {
        "notification_id": "9",
        "recipient_user_id": "198",
        "event_type": "new_mention",
        "message": "Alert 9 for user.",
        "related_entity_type": "pages",
        "related_entity_id": null,
        "sender_user_id": "283",
        "channel": "email",
        "delivery_status": "pending",
        "created_at": "2023-10-31T08:59:21",
        "sent_at": null,
        "read_at": null,
        "metadata": "{\"is_priority\": \"false\"}"
    },
    "10": {
        "notification_id": "10",
        "recipient_user_id": "133",
        "event_type": "new_mention",
        "message": "Alert 10 for user.",
        "related_entity_type": "users",
        "related_entity_id": null,
        "sender_user_id": "255",
        "channel": "email",
        "delivery_status": "pending",
        "created_at": "2023-10-29T23:36:08",
        "sent_at": null,
        "read_at": null,
        "metadata": "{\"is_priority\": \"true\"}"
    },
    "11": {
        "notification_id": "11",
        "recipient_user_id": "263",
        "event_type": "page_updated",
        "message": "Alert 11 for user.",
        "related_entity_type": "users",
        "related_entity_id": null,
        "sender_user_id": "136",
        "channel": "email",
        "delivery_status": "pending",
        "created_at": "2023-11-02T14:58:45",
        "sent_at": null,
        "read_at": null,
        "metadata": "{\"is_priority\": \"true\"}"
    },
    "12": {
        "notification_id": "12",
        "recipient_user_id": "91",
        "event_type": "page_updated",
        "message": "Alert 12 for user.",
        "related_entity_type": "users",
        "related_entity_id": null,
        "sender_user_id": "117",
        "channel": "system",
        "delivery_status": "failed",
        "created_at": "2023-11-07T20:07:47",
        "sent_at": "2023-11-09T16:38:35",
        "read_at": null,
        "metadata": "{\"is_priority\": \"true\"}"
    },
    "13": {
        "notification_id": "13",
        "recipient_user_id": "7",
        "event_type": "permission_granted",
        "message": "Alert 13 for user.",
        "related_entity_type": "spaces",
        "related_entity_id": null,
        "sender_user_id": "284",
        "channel": "email",
        "delivery_status": "failed",
        "created_at": "2023-10-31T22:19:58",
        "sent_at": "2023-11-12T01:32:36",
        "read_at": null,
        "metadata": "{\"is_priority\": \"false\"}"
    },
    "14": {
        "notification_id": "14",
        "recipient_user_id": "189",
        "event_type": "permission_granted",
        "message": "Alert 14 for user.",
        "related_entity_type": "pages",
        "related_entity_id": null,
        "sender_user_id": "283",
        "channel": "system",
        "delivery_status": "read",
        "created_at": "2023-11-06T17:29:30",
        "sent_at": "2023-11-14T12:12:58",
        "read_at": "2023-11-20T06:04:35",
        "metadata": "{\"is_priority\": \"false\"}"
    },
    "15": {
        "notification_id": "15",
        "recipient_user_id": "164",
        "event_type": "page_updated",
        "message": "Alert 15 for user.",
        "related_entity_type": "users",
        "related_entity_id": null,
        "sender_user_id": "109",
        "channel": "system",
        "delivery_status": "read",
        "created_at": "2023-10-31T20:17:11",
        "sent_at": "2023-11-17T08:27:37",
        "read_at": "2023-11-21T21:31:06",
        "metadata": "{\"is_priority\": \"true\"}"
    },
    "16": {
        "notification_id": "16",
        "recipient_user_id": "91",
        "event_type": "new_mention",
        "message": "Alert 16 for user.",
        "related_entity_type": "spaces",
        "related_entity_id": null,
        "sender_user_id": "138",
        "channel": "email",
        "delivery_status": "failed",
        "created_at": "2023-11-06T21:03:12",
        "sent_at": "2023-11-14T13:39:59",
        "read_at": null,
        "metadata": "{\"is_priority\": \"false\"}"
    },
    "17": {
        "notification_id": "17",
        "recipient_user_id": "26",
        "event_type": "page_updated",
        "message": "Alert 17 for user.",
        "related_entity_type": "spaces",
        "related_entity_id": null,
        "sender_user_id": "95",
        "channel": "system",
        "delivery_status": "failed",
        "created_at": "2023-11-11T01:02:42",
        "sent_at": "2023-11-18T14:23:30",
        "read_at": null,
        "metadata": "{\"is_priority\": \"false\"}"
    },
    "18": {
        "notification_id": "18",
        "recipient_user_id": "91",
        "event_type": "permission_granted",
        "message": "Alert 18 for user.",
        "related_entity_type": "pages",
        "related_entity_id": null,
        "sender_user_id": "288",
        "channel": "system",
        "delivery_status": "pending",
        "created_at": "2023-10-30T16:14:17",
        "sent_at": null,
        "read_at": null,
        "metadata": "{\"is_priority\": \"false\"}"
    },
    "19": {
        "notification_id": "19",
        "recipient_user_id": "18",
        "event_type": "page_updated",
        "message": "Alert 19 for user.",
        "related_entity_type": "pages",
        "related_entity_id": null,
        "sender_user_id": "247",
        "channel": "email",
        "delivery_status": "failed",
        "created_at": "2023-11-03T16:54:37",
        "sent_at": "2023-11-19T22:47:53",
        "read_at": null,
        "metadata": "{\"is_priority\": \"false\"}"
    },
    "20": {
        "notification_id": "20",
        "recipient_user_id": "32",
        "event_type": "page_updated",
        "message": "Alert 20 for user.",
        "related_entity_type": "users",
        "related_entity_id": null,
        "sender_user_id": "48",
        "channel": "email",
        "delivery_status": "read",
        "created_at": "2023-10-29T09:23:45",
        "sent_at": "2023-11-21T00:03:34",
        "read_at": "2023-11-22T14:58:24",
        "metadata": "{\"is_priority\": \"false\"}"
    },
    "21": {
        "notification_id": "21",
        "recipient_user_id": "110",
        "event_type": "permission_granted",
        "message": "Alert 21 for user.",
        "related_entity_type": "pages",
        "related_entity_id": null,
        "sender_user_id": "179",
        "channel": "email",
        "delivery_status": "sent",
        "created_at": "2023-11-13T11:19:10",
        "sent_at": "2023-11-19T17:11:48",
        "read_at": null,
        "metadata": "{\"is_priority\": \"true\"}"
    },
    "22": {
        "notification_id": "22",
        "recipient_user_id": "190",
        "event_type": "page_updated",
        "message": "Alert 22 for user.",
        "related_entity_type": "spaces",
        "related_entity_id": null,
        "sender_user_id": "71",
        "channel": "email",
        "delivery_status": "pending",
        "created_at": "2023-10-31T15:16:01",
        "sent_at": null,
        "read_at": null,
        "metadata": "{\"is_priority\": \"false\"}"
    },
    "23": {
        "notification_id": "23",
        "recipient_user_id": "223",
        "event_type": "permission_granted",
        "message": "Alert 23 for user.",
        "related_entity_type": "pages",
        "related_entity_id": null,
        "sender_user_id": "29",
        "channel": "email",
        "delivery_status": "read",
        "created_at": "2023-11-01T21:44:06",
        "sent_at": "2023-11-24T11:05:49",
        "read_at": "2023-11-27T17:37:28",
        "metadata": "{\"is_priority\": \"true\"}"
    },
    "24": {
        "notification_id": "24",
        "recipient_user_id": "243",
        "event_type": "permission_granted",
        "message": "Alert 24 for user.",
        "related_entity_type": "users",
        "related_entity_id": null,
        "sender_user_id": "36",
        "channel": "system",
        "delivery_status": "read",
        "created_at": "2023-11-05T08:38:47",
        "sent_at": "2023-11-22T13:00:45",
        "read_at": "2023-11-27T01:25:56",
        "metadata": "{\"is_priority\": \"false\"}"
    },
    "25": {
        "notification_id": "25",
        "recipient_user_id": "104",
        "event_type": "page_updated",
        "message": "Alert 25 for user.",
        "related_entity_type": "pages",
        "related_entity_id": null,
        "sender_user_id": "112",
        "channel": "email",
        "delivery_status": "pending",
        "created_at": "2023-11-05T22:24:35",
        "sent_at": null,
        "read_at": null,
        "metadata": "{\"is_priority\": \"true\"}"
    },
    "26": {
        "notification_id": "26",
        "recipient_user_id": "111",
        "event_type": "new_mention",
        "message": "Alert 26 for user.",
        "related_entity_type": "spaces",
        "related_entity_id": null,
        "sender_user_id": "16",
        "channel": "system",
        "delivery_status": "pending",
        "created_at": "2023-11-01T02:03:59",
        "sent_at": null,
        "read_at": null,
        "metadata": "{\"is_priority\": \"false\"}"
    },
    "27": {
        "notification_id": "27",
        "recipient_user_id": "182",
        "event_type": "permission_granted",
        "message": "Alert 27 for user.",
        "related_entity_type": "users",
        "related_entity_id": null,
        "sender_user_id": "137",
        "channel": "email",
        "delivery_status": "pending",
        "created_at": "2023-11-16T12:08:37",
        "sent_at": null,
        "read_at": null,
        "metadata": "{\"is_priority\": \"false\"}"
    },
    "28": {
        "notification_id": "28",
        "recipient_user_id": "254",
        "event_type": "new_mention",
        "message": "Alert 28 for user.",
        "related_entity_type": "spaces",
        "related_entity_id": null,
        "sender_user_id": "140",
        "channel": "system",
        "delivery_status": "failed",
        "created_at": "2023-11-12T17:32:55",
        "sent_at": "2023-11-28T22:56:24",
        "read_at": null,
        "metadata": "{\"is_priority\": \"false\"}"
    },
    "29": {
        "notification_id": "29",
        "recipient_user_id": "270",
        "event_type": "permission_granted",
        "message": "Alert 29 for user.",
        "related_entity_type": "users",
        "related_entity_id": null,
        "sender_user_id": "73",
        "channel": "email",
        "delivery_status": "sent",
        "created_at": "2023-11-21T18:22:25",
        "sent_at": "2023-11-29T23:35:34",
        "read_at": null,
        "metadata": "{\"is_priority\": \"true\"}"
    },
    "30": {
        "notification_id": "30",
        "recipient_user_id": "73",
        "event_type": "new_mention",
        "message": "Alert 30 for user.",
        "related_entity_type": "pages",
        "related_entity_id": null,
        "sender_user_id": "114",
        "channel": "email",
        "delivery_status": "pending",
        "created_at": "2023-11-09T18:07:58",
        "sent_at": null,
        "read_at": null,
        "metadata": "{\"is_priority\": \"false\"}"
    },
    "31": {
        "notification_id": "31",
        "recipient_user_id": "190",
        "event_type": "new_mention",
        "message": "Alert 31 for user.",
        "related_entity_type": "pages",
        "related_entity_id": null,
        "sender_user_id": "219",
        "channel": "system",
        "delivery_status": "pending",
        "created_at": "2023-11-12T16:55:03",
        "sent_at": null,
        "read_at": null,
        "metadata": "{\"is_priority\": \"false\"}"
    },
    "32": {
        "notification_id": "32",
        "recipient_user_id": "205",
        "event_type": "new_mention",
        "message": "Alert 32 for user.",
        "related_entity_type": "spaces",
        "related_entity_id": null,
        "sender_user_id": "263",
        "channel": "system",
        "delivery_status": "failed",
        "created_at": "2023-11-26T10:21:20",
        "sent_at": "2023-12-03T05:46:32",
        "read_at": null,
        "metadata": "{\"is_priority\": \"false\"}"
    },
    "33": {
        "notification_id": "33",
        "recipient_user_id": "149",
        "event_type": "permission_granted",
        "message": "Alert 33 for user.",
        "related_entity_type": "pages",
        "related_entity_id": null,
        "sender_user_id": "152",
        "channel": "email",
        "delivery_status": "pending",
        "created_at": "2023-10-29T18:47:21",
        "sent_at": null,
        "read_at": null,
        "metadata": "{\"is_priority\": \"true\"}"
    },
    "34": {
        "notification_id": "34",
        "recipient_user_id": "267",
        "event_type": "new_mention",
        "message": "Alert 34 for user.",
        "related_entity_type": "pages",
        "related_entity_id": null,
        "sender_user_id": "14",
        "channel": "system",
        "delivery_status": "failed",
        "created_at": "2023-11-30T12:15:17",
        "sent_at": "2023-12-02T14:26:51",
        "read_at": null,
        "metadata": "{\"is_priority\": \"true\"}"
    },
    "35": {
        "notification_id": "35",
        "recipient_user_id": "12",
        "event_type": "new_mention",
        "message": "Alert 35 for user.",
        "related_entity_type": "users",
        "related_entity_id": null,
        "sender_user_id": "211",
        "channel": "email",
        "delivery_status": "sent",
        "created_at": "2023-11-13T02:59:11",
        "sent_at": "2023-12-02T17:49:27",
        "read_at": null,
        "metadata": "{\"is_priority\": \"false\"}"
    },
    "36": {
        "notification_id": "36",
        "recipient_user_id": "12",
        "event_type": "new_mention",
        "message": "Alert 36 for user.",
        "related_entity_type": "spaces",
        "related_entity_id": null,
        "sender_user_id": "159",
        "channel": "system",
        "delivery_status": "sent",
        "created_at": "2023-11-28T05:08:26",
        "sent_at": "2023-12-04T04:32:37",
        "read_at": null,
        "metadata": "{\"is_priority\": \"false\"}"
    },
    "37": {
        "notification_id": "37",
        "recipient_user_id": "2",
        "event_type": "permission_granted",
        "message": "Alert 37 for user.",
        "related_entity_type": "spaces",
        "related_entity_id": null,
        "sender_user_id": "15",
        "channel": "system",
        "delivery_status": "pending",
        "created_at": "2023-11-18T20:45:22",
        "sent_at": null,
        "read_at": null,
        "metadata": "{\"is_priority\": \"true\"}"
    },
    "38": {
        "notification_id": "38",
        "recipient_user_id": "287",
        "event_type": "new_mention",
        "message": "Alert 38 for user.",
        "related_entity_type": "pages",
        "related_entity_id": null,
        "sender_user_id": "140",
        "channel": "email",
        "delivery_status": "pending",
        "created_at": "2023-11-11T13:28:26",
        "sent_at": null,
        "read_at": null,
        "metadata": "{\"is_priority\": \"false\"}"
    },
    "39": {
        "notification_id": "39",
        "recipient_user_id": "177",
        "event_type": "permission_granted",
        "message": "Alert 39 for user.",
        "related_entity_type": "users",
        "related_entity_id": null,
        "sender_user_id": "267",
        "channel": "system",
        "delivery_status": "sent",
        "created_at": "2023-11-21T13:10:55",
        "sent_at": "2023-12-06T15:40:10",
        "read_at": null,
        "metadata": "{\"is_priority\": \"false\"}"
    },
    "40": {
        "notification_id": "40",
        "recipient_user_id": "281",
        "event_type": "page_updated",
        "message": "Alert 40 for user.",
        "related_entity_type": "spaces",
        "related_entity_id": null,
        "sender_user_id": "262",
        "channel": "system",
        "delivery_status": "sent",
        "created_at": "2023-12-02T21:15:34",
        "sent_at": "2023-12-09T02:10:58",
        "read_at": null,
        "metadata": "{\"is_priority\": \"true\"}"
    },
    "41": {
        "notification_id": "41",
        "recipient_user_id": "102",
        "event_type": "new_mention",
        "message": "Alert 41 for user.",
        "related_entity_type": "users",
        "related_entity_id": null,
        "sender_user_id": "243",
        "channel": "email",
        "delivery_status": "read",
        "created_at": "2023-11-26T22:31:54",
        "sent_at": "2023-12-11T12:14:04",
        "read_at": "2023-12-16T01:30:15",
        "metadata": "{\"is_priority\": \"false\"}"
    },
    "42": {
        "notification_id": "42",
        "recipient_user_id": "89",
        "event_type": "page_updated",
        "message": "Alert 42 for user.",
        "related_entity_type": "pages",
        "related_entity_id": null,
        "sender_user_id": "282",
        "channel": "system",
        "delivery_status": "pending",
        "created_at": "2023-10-29T17:21:16",
        "sent_at": null,
        "read_at": null,
        "metadata": "{\"is_priority\": \"true\"}"
    },
    "43": {
        "notification_id": "43",
        "recipient_user_id": "57",
        "event_type": "permission_granted",
        "message": "Alert 43 for user.",
        "related_entity_type": "users",
        "related_entity_id": null,
        "sender_user_id": "262",
        "channel": "email",
        "delivery_status": "pending",
        "created_at": "2023-11-03T10:44:21",
        "sent_at": null,
        "read_at": null,
        "metadata": "{\"is_priority\": \"false\"}"
    },
    "44": {
        "notification_id": "44",
        "recipient_user_id": "16",
        "event_type": "page_updated",
        "message": "Alert 44 for user.",
        "related_entity_type": "pages",
        "related_entity_id": null,
        "sender_user_id": "288",
        "channel": "email",
        "delivery_status": "read",
        "created_at": "2023-12-08T07:13:30",
        "sent_at": "2023-12-15T16:57:03",
        "read_at": "2023-12-18T18:07:18",
        "metadata": "{\"is_priority\": \"true\"}"
    },
    "45": {
        "notification_id": "45",
        "recipient_user_id": "162",
        "event_type": "page_updated",
        "message": "Alert 45 for user.",
        "related_entity_type": "pages",
        "related_entity_id": null,
        "sender_user_id": "46",
        "channel": "system",
        "delivery_status": "failed",
        "created_at": "2023-11-02T12:37:21",
        "sent_at": "2023-12-12T12:28:24",
        "read_at": null,
        "metadata": "{\"is_priority\": \"false\"}"
    },
    "46": {
        "notification_id": "46",
        "recipient_user_id": "153",
        "event_type": "new_mention",
        "message": "Alert 46 for user.",
        "related_entity_type": "spaces",
        "related_entity_id": null,
        "sender_user_id": "182",
        "channel": "system",
        "delivery_status": "read",
        "created_at": "2023-11-09T17:44:44",
        "sent_at": "2023-12-15T05:39:05",
        "read_at": "2023-12-18T15:05:20",
        "metadata": "{\"is_priority\": \"false\"}"
    },
    "47": {
        "notification_id": "47",
        "recipient_user_id": "292",
        "event_type": "new_mention",
        "message": "Alert 47 for user.",
        "related_entity_type": "pages",
        "related_entity_id": null,
        "sender_user_id": "52",
        "channel": "email",
        "delivery_status": "sent",
        "created_at": "2023-11-04T21:19:05",
        "sent_at": "2023-12-18T03:22:46",
        "read_at": null,
        "metadata": "{\"is_priority\": \"false\"}"
    },
    "48": {
        "notification_id": "48",
        "recipient_user_id": "177",
        "event_type": "new_mention",
        "message": "Alert 48 for user.",
        "related_entity_type": "users",
        "related_entity_id": null,
        "sender_user_id": "183",
        "channel": "email",
        "delivery_status": "failed",
        "created_at": "2023-12-10T20:46:44",
        "sent_at": "2023-12-18T09:49:35",
        "read_at": null,
        "metadata": "{\"is_priority\": \"true\"}"
    },
    "49": {
        "notification_id": "49",
        "recipient_user_id": "96",
        "event_type": "new_mention",
        "message": "Alert 49 for user.",
        "related_entity_type": "pages",
        "related_entity_id": null,
        "sender_user_id": "31",
        "channel": "email",
        "delivery_status": "pending",
        "created_at": "2023-10-29T14:34:07",
        "sent_at": null,
        "read_at": null,
        "metadata": "{\"is_priority\": \"true\"}"
    },
    "50": {
        "notification_id": "50",
        "recipient_user_id": "166",
        "event_type": "page_updated",
        "message": "Alert 50 for user.",
        "related_entity_type": "pages",
        "related_entity_id": null,
        "sender_user_id": "205",
        "channel": "system",
        "delivery_status": "pending",
        "created_at": "2023-12-07T09:33:43",
        "sent_at": null,
        "read_at": null,
        "metadata": "{\"is_priority\": \"true\"}"
    },
    "51": {
        "notification_id": "51",
        "recipient_user_id": "17",
        "event_type": "permission_granted",
        "message": "Alert 51 for user.",
        "related_entity_type": "spaces",
        "related_entity_id": null,
        "sender_user_id": "212",
        "channel": "email",
        "delivery_status": "failed",
        "created_at": "2023-11-27T19:26:04",
        "sent_at": "2023-12-23T05:52:33",
        "read_at": null,
        "metadata": "{\"is_priority\": \"true\"}"
    },
    "52": {
        "notification_id": "52",
        "recipient_user_id": "43",
        "event_type": "page_updated",
        "message": "Alert 52 for user.",
        "related_entity_type": "spaces",
        "related_entity_id": null,
        "sender_user_id": "129",
        "channel": "email",
        "delivery_status": "pending",
        "created_at": "2023-12-15T19:16:47",
        "sent_at": null,
        "read_at": null,
        "metadata": "{\"is_priority\": \"true\"}"
    },
    "53": {
        "notification_id": "53",
        "recipient_user_id": "42",
        "event_type": "new_mention",
        "message": "Alert 53 for user.",
        "related_entity_type": "spaces",
        "related_entity_id": null,
        "sender_user_id": "253",
        "channel": "system",
        "delivery_status": "pending",
        "created_at": "2023-12-18T09:52:34",
        "sent_at": null,
        "read_at": null,
        "metadata": "{\"is_priority\": \"true\"}"
    },
    "54": {
        "notification_id": "54",
        "recipient_user_id": "277",
        "event_type": "new_mention",
        "message": "Alert 54 for user.",
        "related_entity_type": "users",
        "related_entity_id": null,
        "sender_user_id": "6",
        "channel": "email",
        "delivery_status": "sent",
        "created_at": "2023-12-19T13:14:41",
        "sent_at": "2023-12-25T08:23:38",
        "read_at": null,
        "metadata": "{\"is_priority\": \"true\"}"
    },
    "55": {
        "notification_id": "55",
        "recipient_user_id": "214",
        "event_type": "permission_granted",
        "message": "Alert 55 for user.",
        "related_entity_type": "pages",
        "related_entity_id": null,
        "sender_user_id": "58",
        "channel": "system",
        "delivery_status": "failed",
        "created_at": "2023-12-21T23:57:40",
        "sent_at": "2023-12-22T10:22:42",
        "read_at": null,
        "metadata": "{\"is_priority\": \"true\"}"
    },
    "56": {
        "notification_id": "56",
        "recipient_user_id": "23",
        "event_type": "page_updated",
        "message": "Alert 56 for user.",
        "related_entity_type": "users",
        "related_entity_id": null,
        "sender_user_id": "201",
        "channel": "email",
        "delivery_status": "sent",
        "created_at": "2023-12-03T08:47:38",
        "sent_at": "2023-12-26T15:57:02",
        "read_at": null,
        "metadata": "{\"is_priority\": \"true\"}"
    },
    "57": {
        "notification_id": "57",
        "recipient_user_id": "54",
        "event_type": "page_updated",
        "message": "Alert 57 for user.",
        "related_entity_type": "spaces",
        "related_entity_id": null,
        "sender_user_id": "105",
        "channel": "email",
        "delivery_status": "read",
        "created_at": "2023-12-03T14:46:19",
        "sent_at": "2023-12-25T16:05:02",
        "read_at": "2024-01-01T21:55:35",
        "metadata": "{\"is_priority\": \"true\"}"
    },
    "58": {
        "notification_id": "58",
        "recipient_user_id": "247",
        "event_type": "new_mention",
        "message": "Alert 58 for user.",
        "related_entity_type": "spaces",
        "related_entity_id": null,
        "sender_user_id": "22",
        "channel": "email",
        "delivery_status": "failed",
        "created_at": "2023-11-02T05:16:41",
        "sent_at": "2023-12-26T11:30:02",
        "read_at": null,
        "metadata": "{\"is_priority\": \"true\"}"
    },
    "59": {
        "notification_id": "59",
        "recipient_user_id": "64",
        "event_type": "new_mention",
        "message": "Alert 59 for user.",
        "related_entity_type": "pages",
        "related_entity_id": null,
        "sender_user_id": "38",
        "channel": "email",
        "delivery_status": "read",
        "created_at": "2023-12-23T05:23:29",
        "sent_at": "2023-12-29T18:11:28",
        "read_at": "2024-01-04T14:51:32",
        "metadata": "{\"is_priority\": \"true\"}"
    },
    "60": {
        "notification_id": "60",
        "recipient_user_id": "111",
        "event_type": "page_updated",
        "message": "Alert 60 for user.",
        "related_entity_type": "users",
        "related_entity_id": null,
        "sender_user_id": "215",
        "channel": "email",
        "delivery_status": "pending",
        "created_at": "2023-11-08T02:22:50",
        "sent_at": null,
        "read_at": null,
        "metadata": "{\"is_priority\": \"true\"}"
    },
    "61": {
        "notification_id": "61",
        "recipient_user_id": "173",
        "event_type": "new_mention",
        "message": "Alert 61 for user.",
        "related_entity_type": "spaces",
        "related_entity_id": null,
        "sender_user_id": "61",
        "channel": "system",
        "delivery_status": "read",
        "created_at": "2023-12-15T14:26:34",
        "sent_at": "2024-01-01T18:29:14",
        "read_at": "2024-01-06T01:02:22",
        "metadata": "{\"is_priority\": \"false\"}"
    },
    "62": {
        "notification_id": "62",
        "recipient_user_id": "238",
        "event_type": "new_mention",
        "message": "Alert 62 for user.",
        "related_entity_type": "spaces",
        "related_entity_id": null,
        "sender_user_id": "19",
        "channel": "system",
        "delivery_status": "read",
        "created_at": "2023-12-26T01:28:37",
        "sent_at": "2023-12-30T08:16:07",
        "read_at": "2024-01-07T23:46:14",
        "metadata": "{\"is_priority\": \"false\"}"
    },
    "63": {
        "notification_id": "63",
        "recipient_user_id": "81",
        "event_type": "new_mention",
        "message": "Alert 63 for user.",
        "related_entity_type": "users",
        "related_entity_id": null,
        "sender_user_id": "15",
        "channel": "system",
        "delivery_status": "pending",
        "created_at": "2023-12-14T10:46:44",
        "sent_at": null,
        "read_at": null,
        "metadata": "{\"is_priority\": \"true\"}"
    },
    "64": {
        "notification_id": "64",
        "recipient_user_id": "7",
        "event_type": "permission_granted",
        "message": "Alert 64 for user.",
        "related_entity_type": "spaces",
        "related_entity_id": null,
        "sender_user_id": "256",
        "channel": "email",
        "delivery_status": "pending",
        "created_at": "2023-12-09T03:52:57",
        "sent_at": null,
        "read_at": null,
        "metadata": "{\"is_priority\": \"true\"}"
    },
    "65": {
        "notification_id": "65",
        "recipient_user_id": "190",
        "event_type": "new_mention",
        "message": "Alert 65 for user.",
        "related_entity_type": "spaces",
        "related_entity_id": null,
        "sender_user_id": "103",
        "channel": "email",
        "delivery_status": "failed",
        "created_at": "2023-12-10T02:39:33",
        "sent_at": "2024-01-02T03:54:28",
        "read_at": null,
        "metadata": "{\"is_priority\": \"true\"}"
    },
    "66": {
        "notification_id": "66",
        "recipient_user_id": "140",
        "event_type": "page_updated",
        "message": "Alert 66 for user.",
        "related_entity_type": "users",
        "related_entity_id": null,
        "sender_user_id": "100",
        "channel": "email",
        "delivery_status": "sent",
        "created_at": "2023-12-18T08:19:54",
        "sent_at": "2024-01-02T11:48:34",
        "read_at": null,
        "metadata": "{\"is_priority\": \"true\"}"
    },
    "67": {
        "notification_id": "67",
        "recipient_user_id": "160",
        "event_type": "new_mention",
        "message": "Alert 67 for user.",
        "related_entity_type": "users",
        "related_entity_id": null,
        "sender_user_id": "173",
        "channel": "email",
        "delivery_status": "pending",
        "created_at": "2023-11-28T00:01:51",
        "sent_at": null,
        "read_at": null,
        "metadata": "{\"is_priority\": \"false\"}"
    },
    "68": {
        "notification_id": "68",
        "recipient_user_id": "122",
        "event_type": "new_mention",
        "message": "Alert 68 for user.",
        "related_entity_type": "users",
        "related_entity_id": null,
        "sender_user_id": "221",
        "channel": "email",
        "delivery_status": "pending",
        "created_at": "2023-10-30T12:55:13",
        "sent_at": null,
        "read_at": null,
        "metadata": "{\"is_priority\": \"true\"}"
    },
    "69": {
        "notification_id": "69",
        "recipient_user_id": "158",
        "event_type": "page_updated",
        "message": "Alert 69 for user.",
        "related_entity_type": "spaces",
        "related_entity_id": null,
        "sender_user_id": "117",
        "channel": "email",
        "delivery_status": "read",
        "created_at": "2023-11-25T05:27:42",
        "sent_at": "2024-01-08T13:17:21",
        "read_at": "2024-01-12T23:53:31",
        "metadata": "{\"is_priority\": \"true\"}"
    },
    "70": {
        "notification_id": "70",
        "recipient_user_id": "21",
        "event_type": "page_updated",
        "message": "Alert 70 for user.",
        "related_entity_type": "users",
        "related_entity_id": null,
        "sender_user_id": "198",
        "channel": "email",
        "delivery_status": "sent",
        "created_at": "2023-12-23T05:02:18",
        "sent_at": "2024-01-07T21:48:22",
        "read_at": null,
        "metadata": "{\"is_priority\": \"false\"}"
    },
    "71": {
        "notification_id": "71",
        "recipient_user_id": "275",
        "event_type": "page_updated",
        "message": "Alert 71 for user.",
        "related_entity_type": "users",
        "related_entity_id": null,
        "sender_user_id": "179",
        "channel": "system",
        "delivery_status": "sent",
        "created_at": "2023-10-29T07:09:07",
        "sent_at": "2024-01-09T19:36:39",
        "read_at": null,
        "metadata": "{\"is_priority\": \"false\"}"
    },
    "72": {
        "notification_id": "72",
        "recipient_user_id": "133",
        "event_type": "permission_granted",
        "message": "Alert 72 for user.",
        "related_entity_type": "users",
        "related_entity_id": null,
        "sender_user_id": "44",
        "channel": "system",
        "delivery_status": "pending",
        "created_at": "2023-11-30T08:42:17",
        "sent_at": null,
        "read_at": null,
        "metadata": "{\"is_priority\": \"true\"}"
    },
    "73": {
        "notification_id": "73",
        "recipient_user_id": "65",
        "event_type": "new_mention",
        "message": "Alert 73 for user.",
        "related_entity_type": "users",
        "related_entity_id": null,
        "sender_user_id": "218",
        "channel": "email",
        "delivery_status": "sent",
        "created_at": "2023-11-14T02:18:00",
        "sent_at": "2024-01-14T07:33:04",
        "read_at": null,
        "metadata": "{\"is_priority\": \"false\"}"
    },
    "74": {
        "notification_id": "74",
        "recipient_user_id": "170",
        "event_type": "new_mention",
        "message": "Alert 74 for user.",
        "related_entity_type": "users",
        "related_entity_id": null,
        "sender_user_id": "31",
        "channel": "system",
        "delivery_status": "failed",
        "created_at": "2023-11-04T22:35:09",
        "sent_at": "2024-01-10T17:46:43",
        "read_at": null,
        "metadata": "{\"is_priority\": \"false\"}"
    },
    "75": {
        "notification_id": "75",
        "recipient_user_id": "297",
        "event_type": "page_updated",
        "message": "Alert 75 for user.",
        "related_entity_type": "spaces",
        "related_entity_id": null,
        "sender_user_id": "181",
        "channel": "system",
        "delivery_status": "pending",
        "created_at": "2023-12-02T23:48:58",
        "sent_at": null,
        "read_at": null,
        "metadata": "{\"is_priority\": \"true\"}"
    },
    "76": {
        "notification_id": "76",
        "recipient_user_id": "128",
        "event_type": "new_mention",
        "message": "Alert 76 for user.",
        "related_entity_type": "pages",
        "related_entity_id": null,
        "sender_user_id": "98",
        "channel": "system",
        "delivery_status": "sent",
        "created_at": "2023-12-09T14:11:53",
        "sent_at": "2024-01-13T09:58:53",
        "read_at": null,
        "metadata": "{\"is_priority\": \"false\"}"
    },
    "77": {
        "notification_id": "77",
        "recipient_user_id": "72",
        "event_type": "new_mention",
        "message": "Alert 77 for user.",
        "related_entity_type": "users",
        "related_entity_id": null,
        "sender_user_id": "81",
        "channel": "email",
        "delivery_status": "read",
        "created_at": "2023-12-31T20:45:28",
        "sent_at": "2024-01-15T18:07:43",
        "read_at": "2024-01-19T10:13:03",
        "metadata": "{\"is_priority\": \"false\"}"
    },
    "78": {
        "notification_id": "78",
        "recipient_user_id": "246",
        "event_type": "new_mention",
        "message": "Alert 78 for user.",
        "related_entity_type": "pages",
        "related_entity_id": null,
        "sender_user_id": "93",
        "channel": "system",
        "delivery_status": "pending",
        "created_at": "2023-12-22T07:11:48",
        "sent_at": null,
        "read_at": null,
        "metadata": "{\"is_priority\": \"false\"}"
    },
    "79": {
        "notification_id": "79",
        "recipient_user_id": "81",
        "event_type": "new_mention",
        "message": "Alert 79 for user.",
        "related_entity_type": "spaces",
        "related_entity_id": null,
        "sender_user_id": "172",
        "channel": "system",
        "delivery_status": "read",
        "created_at": "2023-12-03T15:56:09",
        "sent_at": "2024-01-19T20:09:10",
        "read_at": "2024-01-21T19:43:59",
        "metadata": "{\"is_priority\": \"true\"}"
    },
    "80": {
        "notification_id": "80",
        "recipient_user_id": "44",
        "event_type": "new_mention",
        "message": "Alert 80 for user.",
        "related_entity_type": "spaces",
        "related_entity_id": null,
        "sender_user_id": "158",
        "channel": "system",
        "delivery_status": "failed",
        "created_at": "2023-12-09T08:49:46",
        "sent_at": "2024-01-21T01:20:05",
        "read_at": null,
        "metadata": "{\"is_priority\": \"false\"}"
    },
    "81": {
        "notification_id": "81",
        "recipient_user_id": "162",
        "event_type": "permission_granted",
        "message": "Alert 81 for user.",
        "related_entity_type": "pages",
        "related_entity_id": null,
        "sender_user_id": "280",
        "channel": "email",
        "delivery_status": "sent",
        "created_at": "2023-12-25T17:34:59",
        "sent_at": "2024-01-19T08:38:44",
        "read_at": null,
        "metadata": "{\"is_priority\": \"true\"}"
    },
    "82": {
        "notification_id": "82",
        "recipient_user_id": "262",
        "event_type": "permission_granted",
        "message": "Alert 82 for user.",
        "related_entity_type": "spaces",
        "related_entity_id": null,
        "sender_user_id": "32",
        "channel": "email",
        "delivery_status": "failed",
        "created_at": "2023-11-22T11:59:24",
        "sent_at": "2024-01-21T17:26:22",
        "read_at": null,
        "metadata": "{\"is_priority\": \"false\"}"
    },
    "83": {
        "notification_id": "83",
        "recipient_user_id": "163",
        "event_type": "page_updated",
        "message": "Alert 83 for user.",
        "related_entity_type": "users",
        "related_entity_id": null,
        "sender_user_id": "5",
        "channel": "system",
        "delivery_status": "failed",
        "created_at": "2023-11-08T13:57:07",
        "sent_at": "2024-01-22T11:32:52",
        "read_at": null,
        "metadata": "{\"is_priority\": \"false\"}"
    },
    "84": {
        "notification_id": "84",
        "recipient_user_id": "23",
        "event_type": "permission_granted",
        "message": "Alert 84 for user.",
        "related_entity_type": "pages",
        "related_entity_id": null,
        "sender_user_id": "96",
        "channel": "email",
        "delivery_status": "failed",
        "created_at": "2023-12-05T16:24:31",
        "sent_at": "2024-01-25T02:34:01",
        "read_at": null,
        "metadata": "{\"is_priority\": \"true\"}"
    },
    "85": {
        "notification_id": "85",
        "recipient_user_id": "128",
        "event_type": "permission_granted",
        "message": "Alert 85 for user.",
        "related_entity_type": "users",
        "related_entity_id": null,
        "sender_user_id": "146",
        "channel": "system",
        "delivery_status": "read",
        "created_at": "2023-12-07T05:49:42",
        "sent_at": "2024-01-22T04:47:26",
        "read_at": "2024-01-30T14:26:54",
        "metadata": "{\"is_priority\": \"false\"}"
    },
    "86": {
        "notification_id": "86",
        "recipient_user_id": "68",
        "event_type": "permission_granted",
        "message": "Alert 86 for user.",
        "related_entity_type": "users",
        "related_entity_id": null,
        "sender_user_id": "58",
        "channel": "system",
        "delivery_status": "failed",
        "created_at": "2023-12-06T06:29:06",
        "sent_at": "2024-01-23T18:44:28",
        "read_at": null,
        "metadata": "{\"is_priority\": \"false\"}"
    },
    "87": {
        "notification_id": "87",
        "recipient_user_id": "163",
        "event_type": "page_updated",
        "message": "Alert 87 for user.",
        "related_entity_type": "users",
        "related_entity_id": null,
        "sender_user_id": "244",
        "channel": "email",
        "delivery_status": "read",
        "created_at": "2023-12-09T09:35:26",
        "sent_at": "2024-01-24T18:32:37",
        "read_at": "2024-02-01T23:09:24",
        "metadata": "{\"is_priority\": \"true\"}"
    },
    "88": {
        "notification_id": "88",
        "recipient_user_id": "7",
        "event_type": "permission_granted",
        "message": "Alert 88 for user.",
        "related_entity_type": "users",
        "related_entity_id": null,
        "sender_user_id": "73",
        "channel": "email",
        "delivery_status": "pending",
        "created_at": "2024-01-05T17:21:11",
        "sent_at": null,
        "read_at": null,
        "metadata": "{\"is_priority\": \"true\"}"
    },
    "89": {
        "notification_id": "89",
        "recipient_user_id": "290",
        "event_type": "permission_granted",
        "message": "Alert 89 for user.",
        "related_entity_type": "spaces",
        "related_entity_id": null,
        "sender_user_id": "160",
        "channel": "system",
        "delivery_status": "read",
        "created_at": "2023-11-04T17:40:28",
        "sent_at": "2024-01-27T04:48:38",
        "read_at": "2024-01-30T14:24:30",
        "metadata": "{\"is_priority\": \"true\"}"
    },
    "90": {
        "notification_id": "90",
        "recipient_user_id": "284",
        "event_type": "permission_granted",
        "message": "Alert 90 for user.",
        "related_entity_type": "pages",
        "related_entity_id": null,
        "sender_user_id": "147",
        "channel": "email",
        "delivery_status": "pending",
        "created_at": "2023-11-25T23:42:44",
        "sent_at": null,
        "read_at": null,
        "metadata": "{\"is_priority\": \"true\"}"
    },
    "91": {
        "notification_id": "91",
        "recipient_user_id": "264",
        "event_type": "permission_granted",
        "message": "Alert 91 for user.",
        "related_entity_type": "spaces",
        "related_entity_id": null,
        "sender_user_id": "175",
        "channel": "system",
        "delivery_status": "read",
        "created_at": "2024-01-23T07:18:12",
        "sent_at": "2024-01-31T06:48:11",
        "read_at": "2024-02-04T22:36:51",
        "metadata": "{\"is_priority\": \"true\"}"
    },
    "92": {
        "notification_id": "92",
        "recipient_user_id": "50",
        "event_type": "page_updated",
        "message": "Alert 92 for user.",
        "related_entity_type": "pages",
        "related_entity_id": null,
        "sender_user_id": "194",
        "channel": "email",
        "delivery_status": "failed",
        "created_at": "2023-11-07T10:01:03",
        "sent_at": "2024-01-29T10:46:43",
        "read_at": null,
        "metadata": "{\"is_priority\": \"true\"}"
    },
    "93": {
        "notification_id": "93",
        "recipient_user_id": "38",
        "event_type": "new_mention",
        "message": "Alert 93 for user.",
        "related_entity_type": "users",
        "related_entity_id": null,
        "sender_user_id": "68",
        "channel": "system",
        "delivery_status": "sent",
        "created_at": "2024-01-05T23:18:25",
        "sent_at": "2024-01-30T20:31:27",
        "read_at": null,
        "metadata": "{\"is_priority\": \"true\"}"
    },
    "94": {
        "notification_id": "94",
        "recipient_user_id": "44",
        "event_type": "page_updated",
        "message": "Alert 94 for user.",
        "related_entity_type": "spaces",
        "related_entity_id": null,
        "sender_user_id": "127",
        "channel": "system",
        "delivery_status": "sent",
        "created_at": "2023-11-27T22:45:45",
        "sent_at": "2024-01-30T23:07:35",
        "read_at": null,
        "metadata": "{\"is_priority\": \"false\"}"
    },
    "95": {
        "notification_id": "95",
        "recipient_user_id": "249",
        "event_type": "page_updated",
        "message": "Alert 95 for user.",
        "related_entity_type": "spaces",
        "related_entity_id": null,
        "sender_user_id": "190",
        "channel": "system",
        "delivery_status": "read",
        "created_at": "2024-01-09T16:52:20",
        "sent_at": "2024-02-02T10:30:57",
        "read_at": "2024-02-07T05:05:11",
        "metadata": "{\"is_priority\": \"false\"}"
    },
    "96": {
        "notification_id": "96",
        "recipient_user_id": "129",
        "event_type": "new_mention",
        "message": "Alert 96 for user.",
        "related_entity_type": "users",
        "related_entity_id": null,
        "sender_user_id": "134",
        "channel": "email",
        "delivery_status": "pending",
        "created_at": "2023-11-19T03:40:50",
        "sent_at": null,
        "read_at": null,
        "metadata": "{\"is_priority\": \"true\"}"
    },
    "97": {
        "notification_id": "97",
        "recipient_user_id": "86",
        "event_type": "permission_granted",
        "message": "Alert 97 for user.",
        "related_entity_type": "spaces",
        "related_entity_id": null,
        "sender_user_id": "180",
        "channel": "email",
        "delivery_status": "failed",
        "created_at": "2023-12-07T21:14:32",
        "sent_at": "2024-02-05T23:06:11",
        "read_at": null,
        "metadata": "{\"is_priority\": \"true\"}"
    },
    "98": {
        "notification_id": "98",
        "recipient_user_id": "82",
        "event_type": "new_mention",
        "message": "Alert 98 for user.",
        "related_entity_type": "pages",
        "related_entity_id": null,
        "sender_user_id": "252",
        "channel": "system",
        "delivery_status": "sent",
        "created_at": "2024-01-14T14:03:32",
        "sent_at": "2024-02-08T04:32:14",
        "read_at": null,
        "metadata": "{\"is_priority\": \"true\"}"
    },
    "99": {
        "notification_id": "99",
        "recipient_user_id": "154",
        "event_type": "new_mention",
        "message": "Alert 99 for user.",
        "related_entity_type": "users",
        "related_entity_id": null,
        "sender_user_id": "283",
        "channel": "email",
        "delivery_status": "sent",
        "created_at": "2023-10-30T11:59:19",
        "sent_at": "2024-02-08T03:25:47",
        "read_at": null,
        "metadata": "{\"is_priority\": \"true\"}"
    },
    "100": {
        "notification_id": "100",
        "recipient_user_id": "111",
        "event_type": "page_updated",
        "message": "Alert 100 for user.",
        "related_entity_type": "users",
        "related_entity_id": null,
        "sender_user_id": "232",
        "channel": "email",
        "delivery_status": "pending",
        "created_at": "2024-01-31T11:03:49",
        "sent_at": null,
        "read_at": null,
        "metadata": "{\"is_priority\": \"true\"}"
    }
}